isedit
