Metadata-Version: 2.1
Name: isedit
Version: 0.3.0
Summary: Interactive Score Editor
Home-page: https://github.com/sadigulcelik/isedit
Author: sadigulcelik
Author-email: Sadi Gulcelik <sg3790@columbia.edu>
License:                                  Apache License
Project-URL: repository, https://github.com/sadigulcelik/isedit
Keywords: ipython,widgets,Jupyter,JupyterLab,JupyterLab3
Classifier: Programming Language :: Python :: 3.10
Requires-Python: >=3.7
Provides-Extra: develop
License-File: LICENSE
